hybrid/__init__.py
hybrid/composers.py
hybrid/concurrency.py
hybrid/core.py
hybrid/decomposers.py
hybrid/exceptions.py
hybrid/flow.py
hybrid/package_info.py
hybrid/profiling.py
hybrid/samplers.py
hybrid/testing.py
hybrid/traits.py
hybrid/utils.py
hybrid/reference/__init__.py
hybrid/reference/kerberos.py
hybrid/reference/lattice_lnls.py
hybrid/reference/pa.py
hybrid/reference/pt.py
hybrid/reference/qbsolv.py
dwave_hybrid-0.6.12.dist-info/LICENSE
dwave_hybrid-0.6.12.dist-info/METADATA
dwave_hybrid-0.6.12.dist-info/WHEEL
dwave_hybrid-0.6.12.dist-info/top_level.txt
dwave_hybrid-0.6.12.dist-info/RECORD
