Metadata-Version: 2.1
Name: dwave-hybrid
Version: 0.6.12
Summary: Hybrid Asynchronous Decomposition Solver Framework
Home-page: https://github.com/dwavesystems/dwave-hybrid
Author: D-Wave Systems Inc.
Author-email: radomir@dwavesys.com
License: Apache 2.0
Classifier: License :: OSI Approved :: Apache Software License
Classifier: Operating System :: OS Independent
Classifier: Development Status :: 3 - Alpha
Classifier: Programming Language :: Python :: 3 :: Only
Classifier: Programming Language :: Python :: 3.8
Classifier: Programming Language :: Python :: 3.9
Classifier: Programming Language :: Python :: 3.10
Classifier: Programming Language :: Python :: 3.11
Classifier: Programming Language :: Python :: 3.12
Requires-Python: >=3.8
Provides-Extra: test
License-File: LICENSE
